post_gen/__init__.py
post_gen/command.py
post_gen/files.py
post_gen/gitops.py
post_gen/purge.py
post_gen/runner.py
post_gen/gen_ascii/__init__.py
post_gen/gen_ascii/ascii_art.py
post_gen/gen_ascii/gen.py
post_gen/gen_ascii/frame/__init__.py
post_gen/gen_ascii/frame/border.py
post_gen/gen_ascii/frame/framer.py
post_gen/gen_ascii/frame/width_utils.py
post_gen/utils/__init__.py
post_gen/utils/common/__init__.py
post_gen/utils/common/utils.py
post_gen/utils/config/__init__.py
post_gen/utils/config/config.py
post_gen/utils/logging/__init__.py
post_gen/utils/logging/log_util.py
cookiecutter_postgen-0.2.0.dist-info/METADATA
cookiecutter_postgen-0.2.0.dist-info/WHEEL
cookiecutter_postgen-0.2.0.dist-info/top_level.txt
cookiecutter_postgen-0.2.0.dist-info/RECORD
